markdown_it_pyrs-0.4.0.dist-info/METADATA
markdown_it_pyrs-0.4.0.dist-info/WHEEL
markdown_it_pyrs-0.4.0.dist-info/entry_points.txt
markdown_it_pyrs-0.4.0.dist-info/licenses/LICENSE
markdown_it_pyrs-0.4.0.dist-info/licenses/NOTICE
markdown_it_pyrs/__init__.py
markdown_it_pyrs/cli.py
markdown_it_pyrs/markdown_it_pyrs.pyi
markdown_it_pyrs/py.typed
markdown_it_pyrs/markdown_it_pyrs.cpython-310-i386-linux-gnu.so
markdown_it_pyrs-0.4.0.dist-info/RECORD
