Metadata-Version: 2.3
Name: markdown_it_pyrs
Version: 0.4.0
Classifier: Development Status :: 4 - Beta
Classifier: License :: OSI Approved :: Apache Software License
Classifier: Programming Language :: Rust
Classifier: Programming Language :: Python :: Implementation :: CPython
Classifier: Programming Language :: Python :: Implementation :: PyPy
Classifier: Topic :: Software Development :: Libraries :: Python Modules
Classifier: Topic :: Text Processing :: Markup
Requires-Dist: pytest ; extra == 'testing'
Requires-Dist: pytest-param-files ; extra == 'testing'
Requires-Dist: pytest ; extra == 'benchmarking'
Requires-Dist: pytest-benchmark ; extra == 'benchmarking'
Requires-Dist: markdown-it-py ; extra == 'benchmarking'
Provides-Extra: testing
Provides-Extra: benchmarking
License-File: LICENSE
License-File: NOTICE
Summary: A Python interface for markdown-it.rs, using Rust for blazingly fast Markdown parsing ⚡️
Keywords: markdown,lexer,parser,commonmark,markdown-it
Author-email: Chris Sewell <chrisj_sewell@hotmail.com>
Requires-Python: >=3.9
Project-URL: Homepage, https://github.com/chrisjsewell/markdown-it-pyrs
